altern/__init__.py
altern/api.py
altern-0.1.4.dist-info/METADATA
altern-0.1.4.dist-info/WHEEL
altern-0.1.4.dist-info/top_level.txt
altern-0.1.4.dist-info/RECORD
