Metadata-Version: 2.1
Name: altern
Version: 0.1.4
Summary: A Python package to interact with the altern API
Home-page: https://github.com/alternbits/altern-python
Author: Dariush Abbasi
Author-email: poshtehani@gmail.com
Requires-Dist: requests
